env_scanner/__init__.py
env_scanner/cli.py
env_scanner/generator.py
env_scanner/scanner.py
env_scanner-2.3.2.dist-info/licenses/LICENSE
env_scanner-2.3.2.dist-info/METADATA
env_scanner-2.3.2.dist-info/WHEEL
env_scanner-2.3.2.dist-info/entry_points.txt
env_scanner-2.3.2.dist-info/top_level.txt
env_scanner-2.3.2.dist-info/RECORD
