Metadata-Version: 2.4
Name: env-scanner
Version: 2.3.2
Summary: Automatically scan Python projects for environment variables and generate .env-example files
Home-page: https://github.com/ammarmunir4567/env-scanner
Author: Ammar Munir
Author-email: Ammar Munir <ammarmunir4567@gmail.com>
Maintainer-email: Ammar Munir <ammarmunir4567@gmail.com>
License: MIT
Project-URL: Homepage, https://github.com/ammarmunir4567/env_scanner
Project-URL: Documentation, https://github.com/ammarmunir4567/env_scanner#readme
Project-URL: Repository, https://github.com/ammarmunir4567/env_scanner.git
Project-URL: Bug Tracker, https://github.com/ammarmunir4567/env_scanner/issues
Project-URL: Changelog, https://github.com/ammarmunir4567/env_scanner/blob/main/CHANGELOG.md
Keywords: python,environment,env,dotenv,configuration,environment-variables,scanner,generator
Classifier: Development Status :: 3 - Alpha
Classifier: Intended Audience :: Developers
Classifier: Topic :: Software Development :: Libraries :: Python Modules
Classifier: License :: OSI Approved :: MIT License
Classifier: Programming Language :: Python :: 3
Classifier: Programming Language :: Python :: 3.7
Classifier: Programming Language :: Python :: 3.8
Classifier: Programming Language :: Python :: 3.9
Classifier: Programming Language :: Python :: 3.10
Classifier: Programming Language :: Python :: 3.11
Classifier: Operating System :: OS Independent
Requires-Python: >=3.7
License-File: LICENSE
Provides-Extra: dev
Requires-Dist: pytest>=7.0; extra == "dev"
Requires-Dist: pytest-cov>=4.0; extra == "dev"
Requires-Dist: black>=22.0; extra == "dev"
Requires-Dist: flake8>=4.0; extra == "dev"
Requires-Dist: mypy>=0.900; extra == "dev"
Requires-Dist: pre-commit>=2.20.0; extra == "dev"
Requires-Dist: tox>=3.24.0; extra == "dev"
Provides-Extra: docs
Requires-Dist: sphinx>=4.0; extra == "docs"
Requires-Dist: sphinx-rtd-theme>=1.0; extra == "docs"
Requires-Dist: sphinxcontrib-napoleon>=0.7; extra == "docs"
Dynamic: author
Dynamic: home-page
Dynamic: license-file
Dynamic: requires-python
